coincall/Futures.py
coincall/Options.py
coincall/Public.py
coincall/Referral.py
coincall/User.py
coincall/__init__.py
coincall/client.py
coincall/error.py
coincall/exceptions.py
coincall/utils.py
python_coincall-0.1.0.dist-info/LICENSE
python_coincall-0.1.0.dist-info/METADATA
python_coincall-0.1.0.dist-info/WHEEL
python_coincall-0.1.0.dist-info/top_level.txt
python_coincall-0.1.0.dist-info/RECORD
