Metadata-Version: 2.1
Name: python-coincall
Version: 0.1.0
Summary: Python SDK for Coincall
Home-page: https://docs.coincall.com
Author: coincall_api
Author-email: api@coincall.com
License: UNKNOWN
Platform: UNKNOWN
Classifier: Programming Language :: Python :: 3
Classifier: License :: OSI Approved :: MIT License
Classifier: Operating System :: OS Independent
License-File: LICENSE
Requires-Dist: importlib-metadata
Requires-Dist: httpx[http2]
Requires-Dist: keyring
Requires-Dist: requests
Requires-Dist: Twisted
Requires-Dist: pyOpenSSL
